adk_skills_agent/__init__.py
adk_skills_agent/agent.py
adk_skills_agent/exceptions.py
adk_skills_agent/helpers.py
adk_skills_agent/registry.py
adk_skills_agent/core/__init__.py
adk_skills_agent/core/discovery.py
adk_skills_agent/core/models.py
adk_skills_agent/core/parser.py
adk_skills_agent/core/validator.py
adk_skills_agent/executors/__init__.py
adk_skills_agent/tools/__init__.py
adk_skills_agent/tools/read_reference.py
adk_skills_agent/tools/run_script.py
adk_skills_agent/tools/use_skill.py
adk_skills_agent/utils/__init__.py
adk_skills_agent/utils/markdown.py
adk_skills_agent/utils/yaml_parser.py
adk_skills_agent-0.1.0.dist-info/licenses/LICENSE
adk_skills_agent-0.1.0.dist-info/METADATA
adk_skills_agent-0.1.0.dist-info/WHEEL
adk_skills_agent-0.1.0.dist-info/entry_points.txt
adk_skills_agent-0.1.0.dist-info/top_level.txt
adk_skills_agent-0.1.0.dist-info/RECORD
