Metadata-Version: 2.4
Name: adk-skills-agent
Version: 0.1.0
Summary: Agent Skills support for Google's Agent Development Kit (ADK)
Author: ADK Skills Contributors
License: MIT
Project-URL: Homepage, https://github.com/manojlds/adk-skills
Project-URL: Documentation, https://github.com/manojlds/adk-skills
Project-URL: Repository, https://github.com/manojlds/adk-skills
Project-URL: Issues, https://github.com/manojlds/adk-skills/issues
Keywords: adk,agent,skills,ai,llm,gemini
Classifier: Development Status :: 3 - Alpha
Classifier: Intended Audience :: Developers
Classifier: License :: OSI Approved :: MIT License
Classifier: Programming Language :: Python :: 3
Classifier: Programming Language :: Python :: 3.9
Classifier: Programming Language :: Python :: 3.10
Classifier: Programming Language :: Python :: 3.11
Classifier: Programming Language :: Python :: 3.12
Classifier: Topic :: Software Development :: Libraries :: Python Modules
Requires-Python: >=3.9
License-File: LICENSE
Requires-Dist: pyyaml>=6.0
Requires-Dist: pydantic>=2.0
Provides-Extra: dev
Requires-Dist: pytest>=7.0; extra == "dev"
Requires-Dist: pytest-cov>=4.0; extra == "dev"
Requires-Dist: black>=23.0; extra == "dev"
Requires-Dist: ruff>=0.1; extra == "dev"
Requires-Dist: mypy>=1.0; extra == "dev"
Requires-Dist: types-pyyaml>=6.0; extra == "dev"
Dynamic: license-file
